odoo/addons/repair_sale_order/README.rst
odoo/addons/repair_sale_order/__init__.py
odoo/addons/repair_sale_order/__manifest__.py
odoo/addons/repair_sale_order/i18n/it.po
odoo/addons/repair_sale_order/i18n/repair_sale_order.pot
odoo/addons/repair_sale_order/models/__init__.py
odoo/addons/repair_sale_order/models/repair_order.py
odoo/addons/repair_sale_order/models/repair_type.py
odoo/addons/repair_sale_order/models/sale_order.py
odoo/addons/repair_sale_order/readme/CONTRIBUTORS.rst
odoo/addons/repair_sale_order/readme/DESCRIPTION.rst
odoo/addons/repair_sale_order/readme/ROADMAP.rst
odoo/addons/repair_sale_order/readme/USAGE.rst
odoo/addons/repair_sale_order/static/description/icon.png
odoo/addons/repair_sale_order/static/description/index.html
odoo/addons/repair_sale_order/tests/__init__.py
odoo/addons/repair_sale_order/tests/test_repair_sale_order.py
odoo/addons/repair_sale_order/views/repair_order_view.xml
odoo/addons/repair_sale_order/views/repair_type_view.xml
odoo/addons/repair_sale_order/views/sale_order_view.xml
odoo14_addon_repair_sale_order-14.0.1.0.2.dist-info/METADATA
odoo14_addon_repair_sale_order-14.0.1.0.2.dist-info/WHEEL
odoo14_addon_repair_sale_order-14.0.1.0.2.dist-info/top_level.txt
odoo14_addon_repair_sale_order-14.0.1.0.2.dist-info/RECORD
